{
  "title": "9.29Hz World Tour - London",
  "venue": "The O2 Arena",
  "date": "2025-02-16",
  "shenshen": {
    "words": [],
    "behind_the_scenes": [
      {
        "type": "video",
        "title": "【周深9.29Hz世巡】伦敦站倒计时 2天",
        "youtube_url": "https://www.youtube.com/watch?v=fGG55vrhNgQ",
        "bilibili_url": "https://www.bilibili.com/video/BV1EhKjeEEbA"
      },
      {
        "type": "video",
        "title": "【周深9.29Hz世巡Vlog】同频时刻特别记录：谢谢每一个同频的你",
        "youtube_url": "https://www.youtube.com/watch?v=SflEJN_ULy4",
        "bilibili_url": "https://www.bilibili.com/video/BV1JwEezREMX"
      }
    ],
    "media_interviews": [],
    "playlist": []
  },
  "fans": {
    "fan_support": [
      {
        "type": "video",
        "title": "【世巡应援】伦敦告白：爱你不是虚构，不需要理由",
        "youtube_url": "https://youtu.be/k3Oaaj7-q90?si=UFml1OBLod22WAIK",
        "bilibili_url": "https://b23.tv/HzzIGZm"
      },
      {
        "type": "video",
        "title": "【世巡应援】伦敦 | 北美海米相聚伦敦子午线",
        "youtube_url": "https://www.youtube.com/watch?v=LVgHSnSxjaw",
        "bilibili_url": "https://b23.tv/iZvmTA2"
      },
      {
        "type": "video",
        "title": "【世巡应援】伦敦 | 愿深深早日康复！海米爱你",
        "youtube_url": "https://www.youtube.com/watch?v=1kB4oE5NVJs",
        "bilibili_url": "https://b23.tv/JfG2BIs"
      }
    ]
  }
}